batsim_py/__init__.py
batsim_py/__version__.py
batsim_py/events.py
batsim_py/jobs.py
batsim_py/monitors.py
batsim_py/protocol.py
batsim_py/resources.py
batsim_py/simulator.py
batsim_py/utils.py
tests/__init__.py
tests/test_jobs.py
tests/test_monitors.py
tests/test_protocol.py
tests/test_resources.py
tests/test_simulator.py
tests/utils.py
batsim_py-1.0.5.dist-info/LICENSE
batsim_py-1.0.5.dist-info/METADATA
batsim_py-1.0.5.dist-info/WHEEL
batsim_py-1.0.5.dist-info/top_level.txt
batsim_py-1.0.5.dist-info/RECORD
