Metadata-Version: 2.1
Name: batsim-py
Version: 1.0.5
Summary: Batsim-py allows using Batsim from Python 3.
Home-page: https://github.com/lccasagrande/batsim-py
Author: lccasagrande
Author-email: lcamelocasagrande@gmail.com
License: MIT
Download-URL: https://github.com/lccasagrande/batsim-py/archive/v1.0.5.tar.gz
Project-URL: Documentation, https://lccasagrande.github.io/batsim-py/
Project-URL: Tracker, https://github.com/lccasagrande/batsim-py/issues
Keywords: Cluster,Scheduler,Resource and Job Management
Platform: UNKNOWN
Classifier: Programming Language :: Python :: 3
Classifier: Programming Language :: Python :: 3.8
Classifier: Topic :: System :: Clustering
Classifier: Development Status :: 4 - Beta
Classifier: Intended Audience :: Science/Research
Classifier: License :: OSI Approved :: MIT License
Requires-Python: >=3.8
Requires-Dist: zmq (==0.0.0)
Requires-Dist: procset (==1.0)
Requires-Dist: pandas (==0.25.3)
Provides-Extra: dev
Requires-Dist: pytest (==5.4.2) ; extra == 'dev'
Requires-Dist: pytest-mock (==3.1.0) ; extra == 'dev'
Requires-Dist: coveralls (==2.0.0) ; extra == 'dev'
Requires-Dist: jupyter ; extra == 'dev'
Provides-Extra: docs
Requires-Dist: sphinx (>=3.0.1) ; extra == 'docs'
Requires-Dist: sphinx-autodoc-typehints (>=1.10.3) ; extra == 'docs'
Requires-Dist: sphinx-copybutton (>=0.2.10) ; extra == 'docs'
Requires-Dist: sphinx-rtd-theme (>=0.4.3) ; extra == 'docs'
Requires-Dist: ipykernel (==5.1.4) ; extra == 'docs'
Requires-Dist: ipython (==7.13.0) ; extra == 'docs'
Requires-Dist: nbsphinx (==0.6.1) ; extra == 'docs'
Requires-Dist: nbconvert (==5.6.1) ; extra == 'docs'
Requires-Dist: pandoc (==1.0.2) ; extra == 'docs'
